nd2_extractor/__init__.py
nd2_extractor/nd2_extractor.py
nd2_extractor-0.1.0.dist-info/METADATA
nd2_extractor-0.1.0.dist-info/WHEEL
nd2_extractor-0.1.0.dist-info/entry_points.txt
nd2_extractor-0.1.0.dist-info/top_level.txt
nd2_extractor-0.1.0.dist-info/RECORD
