Metadata-Version: 2.1
Name: nd2-extractor
Version: 0.1.0
Summary: A simple tool to extract ND2 files to Zarr, PNG, or TIFF
Home-page: https://github.com/georgeoshardo/nd2_extractor
Author: Georgeos Hardo
Author-email: gh464@cam.ac.uk
Requires-Dist: pims
Requires-Dist: tabulate
Requires-Dist: pims-nd2
Requires-Dist: opencv-python
Requires-Dist: cowpy
Requires-Dist: celluloid
Requires-Dist: termcolor
Requires-Dist: tqdm
Requires-Dist: joblib
Requires-Dist: ipywidgets
Requires-Dist: tifffile
Requires-Dist: pandas
Requires-Dist: pyyaml
Requires-Dist: zarr
